gai/__init__.py
gai/agent.py
gai/chat.py
gai/cli.py
gai/completer.py
gai/config.py
gai/context.py
gai/fs.py
gai/gemini.py
gai/info.txt
gai/languages.py
gai/scanner.py
gai/themes.py
gai/ui.py
gai_ag-2.0.0.dist-info/METADATA
gai_ag-2.0.0.dist-info/WHEEL
gai_ag-2.0.0.dist-info/entry_points.txt
gai_ag-2.0.0.dist-info/top_level.txt
gai_ag-2.0.0.dist-info/RECORD
