Metadata-Version: 2.4
Name: gai-ag
Version: 2.0.0
Summary: A production-ready Python CLI tool for Google AI Studio.
Author-email: Bugra Akdemir <akdemirbugra5@gmail.com>
License: MIT
Project-URL: Homepage, https://github.com/bugraakdemir/gai-cli
Project-URL: Bug Tracker, https://github.com/bugraakdemir/gai-cli/issues
Classifier: Programming Language :: Python :: 3
Classifier: License :: OSI Approved :: MIT License
Classifier: Operating System :: OS Independent
Requires-Python: >=3.10
Requires-Dist: typer[all]>=0.9.0
Requires-Dist: rich>=13.0.0
Requires-Dist: google-genai>=0.1.0
Requires-Dist: prompt_toolkit>=3.0.0
